---
title: "资源访问受限--引论"
date: 2020-05-20
categories: [java]
tags: [concurrency]
author: "wangy325"
weight: 3
BookToC: false
---


在[线程与任务](./1线程与任务_1.md)文中，虽然创建了多线程，并且线程之间出现了一些**不可预测**的CPU调度，但是由于线程之间是**相互隔离**的——**线程没有访问共同的资源**，尽管在执行任务的过程可能被CPU剥夺运行权，但是当它们再次获得运行权时对运行结果并没有影响，它们是安全的。

> 实际上，上篇文章通过`join()`方法演示了[一种安全访问共享资源的方法](./1线程与任务_2.md/#简单的无锁同步)。

考虑一种情况，如果**多个线程访问同一资源**，并对资源内容进行修改，会发生什么情况？

对于**非原子性**操作，多线程下会出现**竞争条件**。例如，对于操作`accounts[to] += amount`，可以被拆分为多个CPU指令：

1. 加载accounts[to]到寄存器
2. 增加amount
3. 将结果写回acounts[to]

上述3个步骤中，线程执行到**任一步骤**时都可能被剥夺运行权。

如此一来，最后的结果就变得不可预测。

<!--more-->

考虑一个经典的“转账”示例：

```java
public class UnsynchronizedTransfer {

    public static void main(String[] args) {
        double INITIAL_MONEY = 1000;
        int ACCOUNTS = 100;
        Bank bank = new Bank(ACCOUNTS, INITIAL_MONEY);
				// 可以增加循环次数观察“出错”的概率提升
        for (int i = 0; i < 2; i++) {
          	// 多个线程使用同一个bank资源
            Thread t = new Thread(new TransferTask(bank));
            t.start();
        }
    }

    static class TransferTask implements Runnable {
        private Bank bank;
        private int size;
        private double maxAmount = 1000;

        public TransferTask(Bank bank) {
            this.bank = bank;
            this.size = bank.size();
        }

        @Override
        public void run() {
            try {
                int from = (int) (size * Math.random());
                int to = (int) (size * Math.random());
                double amount = maxAmount * Math.random();
                bank.transfer(from, to, amount);
                Thread.sleep((long) (size * Math.random()));
            }catch (InterruptedException e){
                // e.printStackTrace();
            }
        }
    }

    static class Bank {
        private final double[] accounts;

        public Bank(int accountCount, double money) {
            // initialize bank account
            accounts = new double[accountCount];
            Arrays.fill(accounts, money);
        }

        public void transfer(int from, int to, double amount) {
            if (accounts[from] < amount) return;
            if (from == to) return;
            // transfer
            accounts[from] -= amount;
          	// 这句打印语句增加了调度器剥夺线程运行权的风险
            System.out.println(Thread.currentThread() + " move away");
            accounts[to] += amount;
            System.out.printf("%s: %10.2f from %d to %d, Total Balance: %10.2f%n",
                Thread.currentThread(),
                amount,
                from,
                to,
                totalBalance());
        }

        private double totalBalance() {
            double sum = 0;
            for (double a : accounts) {
                sum += a;
            }
            return sum;
        }

        int size() {
            return accounts.length;
        }
    }
}
/* output（sample）:
Thread[Thread-1,5,main] move away
Thread[Thread-0,5,main] move away
Thread[Thread-1,5,main]:     217.65 from 30 to 20, Total Balance:   99445.52
Thread[Thread-0,5,main]:     554.48 from 55 to 53, Total Balance:  100000.00
*///：～
```

上例中，使用多个线程访问了Bank类的资源，在Bank类的`transfer()`方法中，额外增加了一句控制台输出，这是为了增加线程被调度的可能性[^1] （如果注释这句，会发现程序异常的概率会变小）。Bank类初始化时分配100个“账户”，每个账户1000元，然后不断转账，观察所有账户总额的变化。

[^1]: 一般看来，任务越耗时，其被CPU调度剥夺运行权的几率越大。

仔细观察输出（循环2次，出现的概率较小），我们看到:

1. 线程1在输出 *move away* 之后被剥夺运行权；

2. 接着线程0在 *move away* 之后也被剥夺运行权；

3. 线程1继续运行，此时问题就出现了，总金额不是100000：

   在计算总额时，线程1获取账户55的余额时少了554.48元，这正是第2步中线程0的`accounts[from] -= amount`将账户55的余额减少的金额。

实际上CPU的调度过程比上述分析复杂得多，在Bank类的transfer()方法中，**每一行代码在运行时都可能被剥夺运行权**，值得一提的是，上例输出操作的还不是相同的“账户”，若是操作同样的“账户”，情况将变得更复杂。

所以说线程不安全是一种**不确定性**，在有限的线程时，它可能发生也可能不发生，比如main()方法里只循环1次时就不会发生，循环100次就极大概率会发生。并发编程就是要**消除这种不确定性**。

<span id = "evenGenerator">接下来的示例</span>，演示一个生成偶数的工具类，在多线程条件下调用生成偶数的方法并加以判断，若发现不是偶数则退出程序：

```java
public class UnSynchronizedEvenGenerator {
    public static void main(String[] args) {
        System.out.println("press Ctrl-C to exit");
        EvenGenerator evenGenerator = new EvenGenerator();
        ExecutorService executorService = Executors.newCachedThreadPool();
        for (int i = 0; i < 3; i++) {
           executorService.execute(new Thread(new EvenTask(evenGenerator)));
        }
        executorService.shutdown();
    }

    static abstract class AbstractIntGenerator {
        // 此处使用了volatile关键字
        private volatile boolean canceled = false;

        public abstract int next();

        public void cancel() {
            canceled = true;
        }

        public boolean isCanceled() {
            return canceled;
        }
    }


    static class EvenGenerator extends AbstractIntGenerator {
        private int even = 0;

        @Override
        public int next() {
            ++even;  // danger here!
            ++even;
            return even;
        }
    }

    static class EvenTask implements Runnable {
        private EvenGenerator evenGenerator;

        public EvenTask(EvenGenerator evenGenerator) {
            this.evenGenerator = evenGenerator;
        }

        @Override
        public void run() {
            while (!evenGenerator.isCanceled()) {
                int next = evenGenerator.next();
                if (next % 2 != 0) {
                    System.out.println(Thread.currentThread().toString() + next + " not even!");
                    evenGenerator.cancel();
                }
            }
        }
    }
}
/* output: (sample)
press Ctrl-C to exit
Thread[pool-1-thread-2,5,main]1427 not even!
Thread[pool-1-thread-1,5,main]1425 not even!
Thread[pool-1-thread-3,5,main]1429 not even!
*///:~
```

上例中，使用`for`循环开启了多个线程，并使用同一个`evenGenerator`对象作为构造器参数：

```java
for (int i = 0; i < 3; i++) {
   executorService.execute(new Thread(new EvenTask(evenGenerator)));
}
```

当循环次数为1（只有一个线程）时，程序会一直执行，直到按下Ctrl-C手动结束任务；

而当循环次数大于1时，无论其运行多长时间，其总会结束。

AbstractIntGenerator类中的canceled标志是基本数据类型，而Java内存模型规定，所有**原始类型对象（除了double和long）的读写都是原子的**[^2]；~~并且由**volatile**修饰，说明其是**可见的**，因此当发生错误时，所有线程都能读取到cancel信息而退出~~。

[^2]: https://docs.oracle.com/javase/specs/jls/se15/html/jls-17.html#jls-17.7


> 这个表述没错，程序确实也退出了，但是不够严谨。
>
> 查看示例输出可以看到，有3个线程的输出信息，按照输出顺序可以作如下推测：
>
> 1. 线程2发现奇数，修改cancel为true
>
> 2. 线程1发现奇数，修改cancel为true
>
> 嗯？为什么线程1还会执行？根据volatile的语义，线程1不是应该“发现”线程1对cancel的改动么？
>
> 实际上volatile的语义只能保证在线程2之后执行的语句能够发现对cancel的改动。
>
> 但是由于run()方法没有任何同步，所以线程2可能是在线程1while执行之后剥夺线程1的运行权而运行的。
>
> > **2022.05.11注**：实际上是volotile关键字的特性，其能保证可见性，但是不能保证有序性。

EvenGenerator类中通过两次**自增运算**获取下一个偶数，但是**自增运算也不是原子性操作**，其仍可被拆分为多个CPU指令[^3]，并且被调度器剥夺运行权，在多线程下问题就会显现。

[^3]: java文件编译的字节码会对Java代码进行拆分

> 如何确定自增运算不是原子性的呢？

 以下是`javap -c -v UnSynchronizedEvenGenerator\$EvenGenerator`输出的<span id ="byteCode">字节码</span>（部分）

```java
public int next();
 descriptor: ()I
 flags: ACC_PUBLIC
 Code:
   stack=3, locals=1, args_size=1
      0: aload_0
      1: dup
      2: getfield      #2                  // Field even:I
      5: iconst_1
      6: iadd
      7: putfield      #2                  // Field even:I
     10: aload_0
     11: dup
     12: getfield      #2                  // Field even:I
     15: iconst_1
     16: iadd
     17: putfield      #2                  // Field even:I
     20: aload_0
     21: getfield      #2                  // Field even:I
     24: ireturn
```

 可以看到，一个自增操作被拆分为至少[^4]3个步骤：

 [^4]: 尚不清楚前面aload_0以及dup的意义。

 1. get字段even
 2. add修改even
 3. put设置even

在未同步的情况下，其中执行到其中任何一步的时候都可能被CPU剥夺运行权。

如何解决多线程下共享资源的竞争条件呢？

基本上所有的并发模式在解决线程冲突问题时，都采用**序列化访问共享资源**的方式。即同一时刻只允许某一个线程访问资源，其他线程被阻塞。通常是通过在代码前面加上一条**锁语句**来实现的，由于锁产生了一种互斥的效果，这种机制也被称为**互斥量**（ *mutex* ）。











